labrad/LICENSE.txt
labrad/__init__.py
labrad/async.py
labrad/auth.py
labrad/backend.py
labrad/client.py
labrad/concurrent.py
labrad/constants.py
labrad/crypto.py
labrad/decorators.py
labrad/devices.py
labrad/errors.py
labrad/gpib.py
labrad/grammar.py
labrad/manager.py
labrad/oauth.py
labrad/protocol.py
labrad/ratio.py
labrad/server.py
labrad/stream.py
labrad/support.py
labrad/thread.py
labrad/units.py
labrad/version.py
labrad/wrappers.py
labrad/node/__init__.py
labrad/node/__main__.py
labrad/node/launchable-server.ini
labrad/node/node_test.py
labrad/node/server_config.py
labrad/node/server_config_test.py
labrad/servers/__init__.py
labrad/servers/dying_test_server.py
labrad/servers/gpibMockDeviceServer.py
labrad/servers/loop_server.py
labrad/servers/registry_wrapper_async.py
labrad/servers/server_template.py
labrad/servers/super_node.py
labrad/servers/test_server.py
labrad/servers/test_server_local.py
labrad/servers/threaded_test_server.py
labrad/test/__init__.py
labrad/test/extraction_test.py
labrad/test/test_client.py
labrad/test/test_concurrent.py
labrad/test/test_crypto.py
labrad/test/test_decorators.py
labrad/test/test_eval_lr_data.py
labrad/test/test_refresh.py
labrad/test/test_server.py
labrad/test/test_signal.py
labrad/test/test_tls.py
labrad/test/test_types.py
labrad/test/test_units.py
labrad/test/unit_performance.py
labrad/test/util.py
labrad/types/__init__.py
labrad/types/types.py
labrad/util/__init__.py
labrad/util/cache.py
labrad/util/hydrant.py
labrad/util/mux.py
labrad/util/qt4reactor.py
labrad/util/unwrap.py
pylabrad-0.98.3.dist-info/METADATA
pylabrad-0.98.3.dist-info/WHEEL
pylabrad-0.98.3.dist-info/top_level.txt
pylabrad-0.98.3.dist-info/RECORD
